{
  "request": {
    "schemaVersion": "1.0",
    "asOfUnixMs": 1769299200000,
    "market": {
      "symbol": "SOLUSDC",
      "timeframe": "1h",
      "candles": [
        {
          "unixMs": 1769173200000,
          "open": 99.8,
          "high": 100.9,
          "low": 99,
          "close": 100,
          "volume": 1000
        },
        {
          "unixMs": 1769176800000,
          "open": 100.03263363615538,
          "high": 101.13263363615539,
          "low": 99.23263363615538,
          "close": 100.23263363615538,
          "volume": 1010
        },
        {
          "unixMs": 1769180400000,
          "open": 100.86204376368367,
          "high": 101.96204376368368,
          "low": 100.06204376368368,
          "close": 101.06204376368368,
          "volume": 1020
        },
        {
          "unixMs": 1769184000000,
          "open": 100.32976518176947,
          "high": 101.42976518176948,
          "low": 99.52976518176948,
          "close": 100.52976518176948,
          "volume": 1030
        },
        {
          "unixMs": 1769187600000,
          "open": 101.60632548163598,
          "high": 102.70632548163599,
          "low": 100.80632548163598,
          "close": 101.80632548163598,
          "volume": 1040
        },
        {
          "unixMs": 1769191200000,
          "open": 100.19448954930212,
          "high": 101.29448954930213,
          "low": 99.39448954930212,
          "close": 100.39448954930212,
          "volume": 1050
        },
        {
          "unixMs": 1769194800000,
          "open": 101.8511569121908,
          "high": 102.95115691219081,
          "low": 101.0511569121908,
          "close": 102.0511569121908,
          "volume": 1060
        },
        {
          "unixMs": 1769198400000,
          "open": 99.54770305808599,
          "high": 100.647703058086,
          "low": 98.74770305808599,
          "close": 99.74770305808599,
          "volume": 1070
        },
        {
          "unixMs": 1769202000000,
          "open": 101.62872715196298,
          "high": 102.72872715196299,
          "low": 100.82872715196298,
          "close": 101.82872715196298,
          "volume": 1080
        },
        {
          "unixMs": 1769205600000,
          "open": 98.52934400967185,
          "high": 99.62934400967185,
          "low": 97.72934400967185,
          "close": 98.72934400967185,
          "volume": 1090
        },
        {
          "unixMs": 1769209200000,
          "open": 101.17131844454941,
          "high": 102.27131844454942,
          "low": 100.37131844454942,
          "close": 101.37131844454942,
          "volume": 1100
        },
        {
          "unixMs": 1769212800000,
          "open": 97.43846754169398,
          "high": 98.53846754169399,
          "low": 96.63846754169398,
          "close": 97.63846754169398,
          "volume": 1110
        },
        {
          "unixMs": 1769216400000,
          "open": 100.81183700563048,
          "high": 101.91183700563049,
          "low": 100.01183700563048,
          "close": 101.01183700563048,
          "volume": 1120
        },
        {
          "unixMs": 1769220000000,
          "open": 96.60518259847508,
          "high": 97.70518259847509,
          "low": 95.80518259847508,
          "close": 96.80518259847508,
          "volume": 1130
        },
        {
          "unixMs": 1769223600000,
          "open": 100.84125409948248,
          "high": 101.94125409948249,
          "low": 100.04125409948249,
          "close": 101.04125409948249,
          "volume": 1140
        },
        {
          "unixMs": 1769227200000,
          "open": 96.24929087040422,
          "high": 97.34929087040423,
          "low": 95.44929087040423,
          "close": 96.44929087040423,
          "volume": 1150
        },
        {
          "unixMs": 1769230800000,
          "open": 101.3840047301189,
          "high": 102.48400473011891,
          "low": 100.5840047301189,
          "close": 101.5840047301189,
          "volume": 1160
        },
        {
          "unixMs": 1769234400000,
          "open": 96.38616210990683,
          "high": 97.48616210990684,
          "low": 95.58616210990684,
          "close": 96.58616210990684,
          "volume": 1170
        },
        {
          "unixMs": 1769238000000,
          "open": 102.34470140216128,
          "high": 103.44470140216129,
          "low": 101.54470140216128,
          "close": 102.54470140216128,
          "volume": 1180
        },
        {
          "unixMs": 1769241600000,
          "open": 96.8201524118586,
          "high": 97.92015241185861,
          "low": 96.0201524118586,
          "close": 97.0201524118586,
          "volume": 1190
        },
        {
          "unixMs": 1769245200000,
          "open": 103.44898147668546,
          "high": 104.54898147668547,
          "low": 102.64898147668546,
          "close": 103.64898147668546,
          "volume": 1200
        },
        {
          "unixMs": 1769248800000,
          "open": 97.22838391846254,
          "high": 98.32838391846255,
          "low": 96.42838391846254,
          "close": 97.42838391846254,
          "volume": 1210
        },
        {
          "unixMs": 1769252400000,
          "open": 104.36099624354256,
          "high": 105.46099624354257,
          "low": 103.56099624354256,
          "close": 104.56099624354256,
          "volume": 1220
        },
        {
          "unixMs": 1769256000000,
          "open": 97.29900934438363,
          "high": 98.39900934438364,
          "low": 96.49900934438364,
          "close": 97.49900934438364,
          "volume": 1230
        },
        {
          "unixMs": 1769259600000,
          "open": 104.82722989594807,
          "high": 105.92722989594807,
          "low": 104.02722989594807,
          "close": 105.02722989594807,
          "volume": 1240
        },
        {
          "unixMs": 1769263200000,
          "open": 96.86475292971363,
          "high": 97.96475292971364,
          "low": 96.06475292971363,
          "close": 97.06475292971363,
          "volume": 1250
        },
        {
          "unixMs": 1769266800000,
          "open": 104.78506145813567,
          "high": 105.88506145813568,
          "low": 103.98506145813568,
          "close": 104.98506145813568,
          "volume": 1260
        },
        {
          "unixMs": 1769270400000,
          "open": 95.97454218229011,
          "high": 97.07454218229012,
          "low": 95.17454218229011,
          "close": 96.17454218229011,
          "volume": 1270
        },
        {
          "unixMs": 1769274000000,
          "open": 104.3895806826657,
          "high": 105.4895806826657,
          "low": 103.5895806826657,
          "close": 104.5895806826657,
          "volume": 1280
        },
        {
          "unixMs": 1769277600000,
          "open": 94.87255587224362,
          "high": 95.97255587224363,
          "low": 94.07255587224363,
          "close": 95.07255587224363,
          "volume": 1290
        },
        {
          "unixMs": 1769281200000,
          "open": 103.94717466693275,
          "high": 105.04717466693276,
          "low": 103.14717466693276,
          "close": 104.14717466693276,
          "volume": 1300
        },
        {
          "unixMs": 1769284800000,
          "open": 93.89366046133212,
          "high": 94.99366046133213,
          "low": 93.09366046133212,
          "close": 94.09366046133212,
          "volume": 1310
        },
        {
          "unixMs": 1769288400000,
          "open": 103.78432509179427,
          "high": 104.88432509179428,
          "low": 102.98432509179428,
          "close": 103.98432509179428,
          "volume": 1320
        },
        {
          "unixMs": 1769292000000,
          "open": 93.32001175213915,
          "high": 94.42001175213916,
          "low": 92.52001175213915,
          "close": 93.52001175213915,
          "volume": 1330
        },
        {
          "unixMs": 1769295600000,
          "open": 104.10780044758141,
          "high": 105.20780044758142,
          "low": 103.30780044758141,
          "close": 104.30780044758141,
          "volume": 1340
        },
        {
          "unixMs": 1769299200000,
          "open": 93.2602285845161,
          "high": 94.36022858451611,
          "low": 92.4602285845161,
          "close": 93.4602285845161,
          "volume": 1350
        }
      ]
    },
    "portfolio": {
      "navUsd": 10000,
      "solUnits": 20,
      "usdcUnits": 6000
    },
    "autopilotState": {
      "activeClmm": false,
      "stopouts24h": 2,
      "redeploys24h": 2,
      "cooldownUntilUnixMs": 1769342400000,
      "standDownUntilUnixMs": 1769385600000,
      "strikeCount": 2
    },
    "config": {
      "regime": {
        "confirmBars": 2,
        "minHoldBars": 3,
        "enterUpTrend": 0.6,
        "exitUpTrend": 0.35,
        "enterDownTrend": -0.6,
        "exitDownTrend": -0.35,
        "chopVolRatioMax": 1.4
      },
      "allocation": {
        "upSolBps": 8000,
        "downSolBps": 1500,
        "chopSolBps": 5000,
        "maxDeltaExposureBpsPerDay": 1000,
        "maxTurnoverPerDayBps": 600
      },
      "churn": {
        "maxStopouts24h": 2,
        "maxRedeploys24h": 2,
        "cooldownMsAfterStopout": 86400000,
        "standDownTriggerStrikes": 2
      },
      "baselines": {
        "dcaIntervalDays": 7,
        "dcaAmountUsd": 250,
        "usdcCarryApr": 0.06
      }
    }
  },
  "execution": {
    "status": "SKIPPED",
    "costs": {
      "txFeesUsd": 0.01,
      "priorityFeesUsd": 0,
      "slippageUsd": 0
    },
    "portfolioAfter": {
      "navUsd": 9900,
      "solUnits": 19.7,
      "usdcUnits": 6060
    }
  }
}
